<?xml version="1.0" encoding="utf-8"?>
<ObjDef xmlns="http://www.sonicretro.org" Namespace="S3KObjectDefinitions.Common" TypeName="Monitor" Language="cs" Name="Monitor" Image="static">
  <Images>
    <ImageFromMappings id="static">
      <ArtFile filename="../Objects/Monitor/KosinskiM Art/Monitors.bin" compression="KosinskiM" />
      <MapFile type="ASM" filename="../Objects/Monitor/Object data/Map - Monitor.asm" frame="1" startpal="0" />
    </ImageFromMappings>
    <ImageFromMappings id="sonic">
      <ArtFile filename="../Objects/Monitor/KosinskiM Art/Monitors.bin" compression="KosinskiM" />
      <MapFile type="ASM" filename="../Objects/Monitor/Object data/Map - Monitor.asm" frame="2" startpal="0" />
    </ImageFromMappings>
    <ImageFromMappings id="eggman">
      <ArtFile filename="../Objects/Monitor/KosinskiM Art/Monitors.bin" compression="KosinskiM" />
      <MapFile type="ASM" filename="../Objects/Monitor/Object data/Map - Monitor.asm" frame="3" startpal="0" />
    </ImageFromMappings>
    <ImageFromMappings id="rings">
      <ArtFile filename="../Objects/Monitor/KosinskiM Art/Monitors.bin" compression="KosinskiM" />
      <MapFile type="ASM" filename="../Objects/Monitor/Object data/Map - Monitor.asm" frame="4" startpal="0" />
    </ImageFromMappings>
    <ImageFromMappings id="shoes">
      <ArtFile filename="../Objects/Monitor/KosinskiM Art/Monitors.bin" compression="KosinskiM" />
      <MapFile type="ASM" filename="../Objects/Monitor/Object data/Map - Monitor.asm" frame="5" startpal="0" />
    </ImageFromMappings>
    <ImageFromMappings id="fire">
      <ArtFile filename="../Objects/Monitor/KosinskiM Art/Monitors.bin" compression="KosinskiM" />
      <MapFile type="ASM" filename="../Objects/Monitor/Object data/Map - Monitor.asm" frame="6" startpal="0" />
    </ImageFromMappings>
    <ImageFromMappings id="lightning">
      <ArtFile filename="../Objects/Monitor/KosinskiM Art/Monitors.bin" compression="KosinskiM" />
      <MapFile type="ASM" filename="../Objects/Monitor/Object data/Map - Monitor.asm" frame="7" startpal="0" />
    </ImageFromMappings>
    <ImageFromMappings id="water">
      <ArtFile filename="../Objects/Monitor/KosinskiM Art/Monitors.bin" compression="KosinskiM" />
      <MapFile type="ASM" filename="../Objects/Monitor/Object data/Map - Monitor.asm" frame="8" startpal="0" />
    </ImageFromMappings>
    <ImageFromMappings id="invincibility">
      <ArtFile filename="../Objects/Monitor/KosinskiM Art/Monitors.bin" compression="KosinskiM" />
      <MapFile type="ASM" filename="../Objects/Monitor/Object data/Map - Monitor.asm" frame="9" startpal="0" />
    </ImageFromMappings>
    <ImageFromMappings id="s">
      <ArtFile filename="../Objects/Monitor/KosinskiM Art/Monitors.bin" compression="KosinskiM" />
      <MapFile type="ASM" filename="../Objects/Monitor/Object data/Map - Monitor.asm" frame="10" startpal="0" />
    </ImageFromMappings>
    <ImageFromMappings id="broken">
      <ArtFile filename="../Objects/Monitor/KosinskiM Art/Monitors.bin" compression="KosinskiM" />
      <MapFile type="ASM" filename="../Objects/Monitor/Object data/Map - Monitor.asm" frame="11" startpal="0" />
    </ImageFromMappings>
  </Images>
  <Subtypes>
    <Subtype id="00" name="Static" image="static" />
    <Subtype id="01" name="Eggman" image="eggman" />
    <Subtype id="02" name="Rings" image="rings" />
    <Subtype id="03" name="Fire Shield" image="shoes" />
    <Subtype id="04" name="Lightning Shield" image="fire" />
    <Subtype id="05" name="Water Shield" image="lightning" />
    <Subtype id="06" name="Blue Shield" image="water" />
	<Subtype id="07" name="Sword" image="invincibility" />
    <Subtype id="08" name="Empty" image="s" />
    <Subtype id="09" name="Random" image="sonic" />
    <Subtype id="0A" name="Broken" image="broken" />
  </Subtypes>
  <Properties>
    <BitsProperty name="Contents" type="MonitorType" startbit="0" length="4" />
  </Properties>
  <Enums>
    <Enum name="MonitorType">
      <EnumMember name="Static" />
      <EnumMember name="Eggman" />
      <EnumMember name="Rings" />
      <EnumMember name="Fire Shield" />
      <EnumMember name="Lightning Shield" />
      <EnumMember name="Water Shield" />
      <EnumMember name="Blue Shield" />
      <EnumMember name="Sword" />
      <EnumMember name="Empty" />
      <EnumMember name="Random" />
      <EnumMember name="Broken" />
    </Enum>
  </Enums>
</ObjDef>